clogger
