Metadata-Version: 2.1
Name: clogger
Version: 0.12.7
Summary: python logger configuration, my way
Home-page: https://github.com/pietrogiuffrida/customlogger/
Author: Pietro Giuffrida
Author-email: pietro.giuffri@gmail.com
License: MIT
Platform: UNKNOWN
Classifier: Programming Language :: Python :: 3
Classifier: License :: OSI Approved :: MIT License
Classifier: Operating System :: OS Independent
